CivilTools/__init__.py
CivilTools/Const/CAD.py
CivilTools/Const/Concrete.py
CivilTools/Const/Steel.py
CivilTools/Const/__init__.py
CivilTools/DXFGenerator/BasicDXF.py
CivilTools/DXFGenerator/DetailDXF.py
CivilTools/DXFGenerator/DrawingAttribs.py
CivilTools/DXFGenerator/LayerManager.py
CivilTools/DXFGenerator/__init__.py
CivilTools/FigureGenerator/BasicPNGPlotter.py
CivilTools/FigureGenerator/BasicPltPlotter.py
CivilTools/FigureGenerator/StairCalculationSheetPNGPlotter.py
CivilTools/FigureGenerator/__init__.py
CivilTools/FigureGenerator/SeismicReport/Drift.py
CivilTools/FigureGenerator/SeismicReport/ShearMassRatio.py
CivilTools/FigureGenerator/SeismicReport/ShearMoment.py
CivilTools/FigureGenerator/SeismicReport/__init__.py
CivilTools/ReportGenerator/BasicGenerator.py
CivilTools/ReportGenerator/DocParagraph.py
CivilTools/ReportGenerator/DocPicture.py
CivilTools/ReportGenerator/DocTable.py
CivilTools/ReportGenerator/SeismicReport.py
CivilTools/ReportGenerator/SeismicReportTemplate.py
CivilTools/ReportGenerator/StairCalculationReport.py
CivilTools/ReportGenerator/UtilFunctions.py
CivilTools/ReportGenerator/__init__.py
CivilTools/YDBLoader/YDBLoader.py
CivilTools/YDBLoader/YDBType.py
CivilTools/YDBLoader/__init__.py
CivilTools/YDBLoader/BuildingDefine/ComponentType.py
CivilTools/YDBLoader/BuildingDefine/__init__.py
CivilTools/YDBLoader/BuildingDefine/Beam/Beam.py
CivilTools/YDBLoader/BuildingDefine/Beam/__init__.py
CivilTools/YDBLoader/BuildingDefine/Column/Column.py
CivilTools/YDBLoader/BuildingDefine/Column/__init__.py
CivilTools/YDBLoader/BuildingDefine/Geometry/Grid.py
CivilTools/YDBLoader/BuildingDefine/Geometry/Joint.py
CivilTools/YDBLoader/BuildingDefine/Geometry/StandFloor.py
CivilTools/YDBLoader/BuildingDefine/Geometry/__init__.py
CivilTools/YDBLoader/BuildingDefine/GlobalResult/BasicResult.py
CivilTools/YDBLoader/BuildingDefine/GlobalResult/SeismicResult.py
CivilTools/YDBLoader/BuildingDefine/GlobalResult/__init__.py
civil_tools_v-0.0.6.dist-info/LICENSE
civil_tools_v-0.0.6.dist-info/METADATA
civil_tools_v-0.0.6.dist-info/WHEEL
civil_tools_v-0.0.6.dist-info/top_level.txt
civil_tools_v-0.0.6.dist-info/RECORD
