Metadata-Version: 2.2
Name: civil_tools_v
Version: 0.0.6
Summary: A powerful tool for civil engineer in their work.
Home-page: https://github.com/VincentXGao/civil-tools
Author: Xinyu Gao (Vincent)
Author-email: just_gxy@163.com
Classifier: Programming Language :: Python :: 3
Classifier: License :: OSI Approved :: MIT License
Classifier: Operating System :: OS Independent
Requires-Python: >=3.6
License-File: LICENSE
Requires-Dist: numpy>=2.0
Requires-Dist: python-docx>=1.0
Requires-Dist: matplotlib>=3.10.0
Requires-Dist: ezdxf==1.4.0
Dynamic: author
Dynamic: author-email
Dynamic: classifier
Dynamic: description
Dynamic: description-content-type
Dynamic: home-page
Dynamic: requires-dist
Dynamic: requires-python
Dynamic: summary
